<?xml version="1.0" encoding="UTF-8" standalone="yes"?><cp:coreProperties xmlns:cp='http://schemas.openxmlformats.org/package/2006/metadata/core-properties' xmlns:dc='http://purl.org/dc/elements/1.1/' xmlns:dcterms='http://purl.org/dc/terms/' xmlns:dcmitype='http://purl.org/dc/dcmitype/'><dc:title>Анатомия человека</dc:title><dc:creator>М. Р. Сапин, Д. Б. Никитюк, В. И. Сивоглазов</dc:creator><cp:revision>1</cp:revision><cp:contentStatus>standalone</cp:contentStatus><cp:category>manual</cp:category><dcterms:modified>2017-09-27T13:20:30</dcterms:modified><dcterms:created>2017-01-16T18:48:44</dcterms:created><dc:subject>учебник для ссузов</dc:subject><dc:description>В данном учебнике излагается курс анатомии человека. Материал учебника изложен на современном научном уровне, в соответствии с современной международной анатомической номенклатурой (2003) и учебной программой и охватывает все разделы анатомии. У учебнике рассматриваются материалы по анатомии клетчаточных пространств, строению и функциям иммунной системы, сопутствующие в преимущественном большинстве аналогичных изданий. Курс анатомии человека излагается в связи с функцией органов и их развитием.Учебник предназначен для учащихся медицинских училищ и колледжей.</dc:description></cp:coreProperties>